bokeh/LICENSE.txt
bokeh/__init__.py
bokeh/__main__.py
bokeh/_specs.pyi
bokeh/_types.pyi
bokeh/driving.py
bokeh/events.py
bokeh/ext.py
bokeh/layouts.py
bokeh/palettes.py
bokeh/py.typed
bokeh/resources.py
bokeh/settings.py
bokeh/transform.py
bokeh/_sri/0.1.0.json
bokeh/_sri/0.10.0.json
bokeh/_sri/0.11.0.json
bokeh/_sri/0.11.1.json
bokeh/_sri/0.12.0.json
bokeh/_sri/0.12.1.json
bokeh/_sri/0.12.10.json
bokeh/_sri/0.12.11.json
bokeh/_sri/0.12.12.json
bokeh/_sri/0.12.13.json
bokeh/_sri/0.12.14.json
bokeh/_sri/0.12.15.json
bokeh/_sri/0.12.16.json
bokeh/_sri/0.12.2.json
bokeh/_sri/0.12.3.json
bokeh/_sri/0.12.4.json
bokeh/_sri/0.12.5.json
bokeh/_sri/0.12.6.json
bokeh/_sri/0.12.7.json
bokeh/_sri/0.12.8.json
bokeh/_sri/0.12.9.json
bokeh/_sri/0.13.0.json
bokeh/_sri/0.2.0.json
bokeh/_sri/0.3.0.json
bokeh/_sri/0.4.0.json
bokeh/_sri/0.4.1.json
bokeh/_sri/0.4.2.json
bokeh/_sri/0.4.3.json
bokeh/_sri/0.4.4.json
bokeh/_sri/0.5.0.json
bokeh/_sri/0.5.1.json
bokeh/_sri/0.5.2.json
bokeh/_sri/0.6.0.json
bokeh/_sri/0.6.1.json
bokeh/_sri/0.7.0.json
bokeh/_sri/0.7.1.json
bokeh/_sri/0.8.0.json
bokeh/_sri/0.8.1.json
bokeh/_sri/0.8.2.json
bokeh/_sri/0.9.0.json
bokeh/_sri/0.9.1.json
bokeh/_sri/0.9.2.json
bokeh/_sri/0.9.3.json
bokeh/_sri/1.0.0.json
bokeh/_sri/1.0.1.json
bokeh/_sri/1.0.2.json
bokeh/_sri/1.0.3.json
bokeh/_sri/1.0.4.json
bokeh/_sri/1.1.0.json
bokeh/_sri/1.2.0.json
bokeh/_sri/1.3.0.json
bokeh/_sri/1.3.1.json
bokeh/_sri/1.3.2.json
bokeh/_sri/1.3.4.json
bokeh/_sri/1.4.0.json
bokeh/_sri/2.0.0.json
bokeh/_sri/2.0.1.json
bokeh/_sri/2.0.2.json
bokeh/_sri/2.1.0.json
bokeh/_sri/2.1.1.json
bokeh/_sri/2.2.0.json
bokeh/_sri/2.2.1.json
bokeh/_sri/2.2.2.json
bokeh/_sri/2.3.0.json
bokeh/_sri/2.3.1.json
bokeh/_sri/2.3.2.json
bokeh/_sri/2.3.3.json
bokeh/_sri/2.4.0.json
bokeh/_sri/2.4.1.json
bokeh/_sri/2.4.2.json
bokeh/_sri/2.4.3.json
bokeh/_sri/3.0.0.json
bokeh/_sri/3.0.1.json
bokeh/_sri/3.0.2.json
bokeh/_sri/3.1.0.json
bokeh/_sri/3.1.1.json
bokeh/_sri/3.2.0.json
bokeh/_sri/3.2.1.json
bokeh-3.7.1.dist-info/licenses/LICENSE.txt
bokeh-3.7.1.dist-info/METADATA
bokeh-3.7.1.dist-info/WHEEL
bokeh-3.7.1.dist-info/entry_points.txt
bokeh-3.7.1.dist-info/top_level.txt
bokeh-3.7.1.dist-info/RECORD
