Metadata-Version: 2.4
Name: bokeh
Version: 3.7.1
Summary: Interactive plots and applications in the browser from Python
Author: Bokeh Team
Author-email: info@bokeh.org
License: Copyright (c) Anaconda, Inc., and Bokeh Contributors
Project-URL: homepage, https://bokeh.org
Project-URL: documentation, https://docs.bokeh.org
Project-URL: repository, https://github.com/bokeh/bokeh
Classifier: Development Status :: 5 - Production/Stable
Classifier: Environment :: Console
Classifier: Environment :: Web Environment
Classifier: Intended Audience :: Developers
Classifier: Intended Audience :: Education
Classifier: Intended Audience :: End Users/Desktop
Classifier: Intended Audience :: Financial and Insurance Industry
Classifier: Intended Audience :: Healthcare Industry
Classifier: Intended Audience :: Information Technology
Classifier: Intended Audience :: Legal Industry
Classifier: Intended Audience :: Other Audience
Classifier: Intended Audience :: Science/Research
Classifier: License :: OSI Approved :: BSD License
Classifier: Programming Language :: Python
Classifier: Programming Language :: Python :: 3
Classifier: Programming Language :: Python :: 3 :: Only
Classifier: Programming Language :: Python :: 3.10
Classifier: Programming Language :: Python :: 3.11
Classifier: Programming Language :: Python :: 3.12
Classifier: Programming Language :: Python :: 3.13
Classifier: Programming Language :: JavaScript
Classifier: Topic :: Office/Business
Classifier: Topic :: Office/Business :: Financial
Classifier: Topic :: Scientific/Engineering
Classifier: Topic :: Scientific/Engineering :: Visualization
Classifier: Topic :: Scientific/Engineering :: Mathematics
Classifier: Topic :: Scientific/Engineering :: Information Analysis
Classifier: Topic :: Utilities
Requires-Python: >=3.10
License-File: LICENSE.txt
Requires-Dist: Jinja2>=2.9
Requires-Dist: contourpy>=1.2
Requires-Dist: narwhals>=1.13
Requires-Dist: numpy>=1.16
Requires-Dist: packaging>=16.8
Requires-Dist: pandas>=1.2
Requires-Dist: pillow>=7.1.0
Requires-Dist: PyYAML>=3.10
Requires-Dist: tornado>=6.2; sys_platform != "emscripten"
Requires-Dist: xyzservices>=2021.09.1
Dynamic: license-file
